pagetools/__init__.py
pagetools/cli/__init__.py
pagetools/cli/analytics/__init__.py
pagetools/cli/analytics/get_char_occurence.py
pagetools/cli/analytics/get_codec.py
pagetools/cli/analytics/get_text_count.py
pagetools/cli/management/__init__.py
pagetools/cli/management/cull.py
pagetools/cli/transformations/__init__.py
pagetools/cli/transformations/change_index.py
pagetools/cli/transformations/extract.py
pagetools/cli/transformations/line2page.py
pagetools/cli/transformations/regularize.py
pagetools/resources/__init__.py
pagetools/resources/rulesets/__init__.py
pagetools/resources/rulesets/ligatures_consonantal.json
pagetools/resources/rulesets/ligatures_vocal.json
pagetools/resources/rulesets/punctuation.json
pagetools/resources/rulesets/quotes.json
pagetools/resources/rulesets/roman_digits.json
pagetools/resources/rulesets/spaces.json
pagetools/resources/rulesets/uvius.json
pagetools/resources/rulesets/various.json
pagetools/src/Image.py
pagetools/src/Page.py
pagetools/src/__init__.py
pagetools/src/extraction/Extractor.py
pagetools/src/extraction/__init__.py
pagetools/src/line2page/Line2Page.py
pagetools/src/line2page/__init__.py
pagetools/src/regularization/Regularizer.py
pagetools/src/regularization/Rules.py
pagetools/src/regularization/__init__.py
pagetools/src/utils/__init__.py
pagetools/src/utils/constants.py
pagetools/src/utils/filesystem.py
pagetools/src/utils/img_processing.py
pagetools/src/utils/page_processing.py
pagetools/tests/__init__.py
pagetools/tests/src/__init__.py
pagetools/tests/src/utils/__init__.py
pagetools/tests/src/utils/test_page_processing.py
PAGETools-0.5.3.dist-info/LICENSE.md
PAGETools-0.5.3.dist-info/METADATA
PAGETools-0.5.3.dist-info/WHEEL
PAGETools-0.5.3.dist-info/entry_points.txt
PAGETools-0.5.3.dist-info/top_level.txt
PAGETools-0.5.3.dist-info/RECORD
