Metadata-Version: 2.1
Name: PAGETools
Version: 0.5.3
Summary: Toolset for performing various operations on PAGE XML datasets.
Author-email: Maximilian Nöth <maximilian.noeth@uni-wuerzburg.de>
License: MIT License
Project-URL: repository, https://github.com/uniwuezpd/PAGETools
Keywords: PAGE XML,OCR,optical character recognition
Classifier: Programming Language :: Python :: 3
Classifier: License :: OSI Approved :: MIT License
Classifier: Operating System :: OS Independent
Requires-Python: >=3.6
License-File: LICENSE.md
Requires-Dist: opencv-python
Requires-Dist: lxml
Requires-Dist: numpy
Requires-Dist: click
Requires-Dist: flake8
Requires-Dist: deskew
Requires-Dist: regex
Requires-Dist: pytest
Requires-Dist: importlib-resources ; python_version < "3.7"
